operacoes/__init__.py
operacoes/base.py
operacoes/divisao.py
operacoes/multiplicacao.py
operacoes/soma.py
operacoes/subtracao.py
calcfastapi_ps-0.1.0.dist-info/METADATA
calcfastapi_ps-0.1.0.dist-info/WHEEL
calcfastapi_ps-0.1.0.dist-info/top_level.txt
calcfastapi_ps-0.1.0.dist-info/RECORD
